stea/__init__.py
stea/stea_client.py
stea/stea_config.py
stea/stea_input.py
stea/stea_keys.py
stea/stea_project.py
stea/stea_request.py
stea/stea_result.py
stea/version.py
stea-0.5.2.dist-info/LICENSE
stea-0.5.2.dist-info/METADATA
stea-0.5.2.dist-info/WHEEL
stea-0.5.2.dist-info/top_level.txt
stea-0.5.2.dist-info/RECORD
